synergy_age_mcp/__init__.py
synergy_age_mcp/server.py
synergy_age_mcp-0.1.0.dist-info/METADATA
synergy_age_mcp-0.1.0.dist-info/WHEEL
synergy_age_mcp-0.1.0.dist-info/entry_points.txt
synergy_age_mcp-0.1.0.dist-info/licenses/LICENSE
synergy_age_mcp-0.1.0.dist-info/RECORD
