Metadata-Version: 2.4
Name: synergy-age-mcp
Version: 0.1.0
Summary: An MCP server for the SynergyAge database - a comprehensive resource for aging and longevity research
Project-URL: Homepage, https://github.com/gerontomics/synergy-age-mcp
Project-URL: Repository, https://github.com/gerontomics/synergy-age-mcp
Project-URL: Bug Tracker, https://github.com/gerontomics/synergy-age-mcp/issues
Project-URL: Original Database, https://github.com/gerontomics/synergyage
Author: SynergyAge MCP Contributors
License: MIT License
License-File: LICENSE
Classifier: Development Status :: 3 - Alpha
Classifier: Intended Audience :: Science/Research
Classifier: License :: OSI Approved :: MIT License
Classifier: Programming Language :: Python :: 3
Classifier: Programming Language :: Python :: 3.10
Classifier: Programming Language :: Python :: 3.11
Classifier: Programming Language :: Python :: 3.12
Classifier: Topic :: Scientific/Engineering :: Bio-Informatics
Classifier: Topic :: Software Development :: Libraries :: Python Modules
Requires-Python: >=3.10
Requires-Dist: aiosqlite>=0.20.0
Requires-Dist: fastmcp>=2.7.0
Requires-Dist: huggingface-hub>=0.32.4
Requires-Dist: pycomfort>=0.0.18
Requires-Dist: pydantic>=2.0.0
Requires-Dist: sqlite-utils>=3.37
Requires-Dist: typing-extensions>=4.5.0
